{
  "id": "88d0e63b-576e-483c-be59-51391f8ff5c4",
  "prevId": "5bfe554a-0567-428b-a45e-120ea2e891dc",
  "version": "7",
  "dialect": "postgresql",
  "tables": {
    "public.auth_codes": {
      "name": "auth_codes",
      "schema": "",
      "columns": {
        "id": {
          "name": "id",
          "type": "uuid",
          "primaryKey": true,
          "notNull": true,
          "default": "gen_random_uuid()"
        },
        "code": {
          "name": "code",
          "type": "text",
          "primaryKey": false,
          "notNull": true
        },
        "user_id": {
          "name": "user_id",
          "type": "uuid",
          "primaryKey": false,
          "notNull": true
        },
        "client_id": {
          "name": "client_id",
          "type": "uuid",
          "primaryKey": false,
          "notNull": true
        },
        "redirect_uri": {
          "name": "redirect_uri",
          "type": "text",
          "primaryKey": false,
          "notNull": true
        },
        "scopes": {
          "name": "scopes",
          "type": "text[]",
          "primaryKey": false,
          "notNull": true
        },
        "used": {
          "name": "used",
          "type": "boolean",
          "primaryKey": false,
          "notNull": true,
          "default": false
        },
        "expires_at": {
          "name": "expires_at",
          "type": "timestamp",
          "primaryKey": false,
          "notNull": true
        },
        "created_at": {
          "name": "created_at",
          "type": "timestamp",
          "primaryKey": false,
          "notNull": true,
          "default": "now()"
        }
      },
      "indexes": {},
      "foreignKeys": {
        "auth_codes_user_id_users_id_fk": {
          "name": "auth_codes_user_id_users_id_fk",
          "tableFrom": "auth_codes",
          "tableTo": "users",
          "columnsFrom": [
            "user_id"
          ],
          "columnsTo": [
            "id"
          ],
          "onDelete": "cascade",
          "onUpdate": "no action"
        },
        "auth_codes_client_id_oauth_clients_id_fk": {
          "name": "auth_codes_client_id_oauth_clients_id_fk",
          "tableFrom": "auth_codes",
          "tableTo": "oauth_clients",
          "columnsFrom": [
            "client_id"
          ],
          "columnsTo": [
            "id"
          ],
          "onDelete": "cascade",
          "onUpdate": "no action"
        }
      },
      "compositePrimaryKeys": {},
      "uniqueConstraints": {},
      "policies": {},
      "checkConstraints": {},
      "isRLSEnabled": false
    },
    "public.consent": {
      "name": "consent",
      "schema": "",
      "columns": {
        "id": {
          "name": "id",
          "type": "uuid",
          "primaryKey": true,
          "notNull": true,
          "default": "gen_random_uuid()"
        },
        "user_id": {
          "name": "user_id",
          "type": "uuid",
          "primaryKey": false,
          "notNull": true
        },
        "client_id": {
          "name": "client_id",
          "type": "uuid",
          "primaryKey": false,
          "notNull": true
        },
        "scopes": {
          "name": "scopes",
          "type": "text[]",
          "primaryKey": false,
          "notNull": true
        },
        "created_at": {
          "name": "created_at",
          "type": "timestamp",
          "primaryKey": false,
          "notNull": true,
          "default": "now()"
        }
      },
      "indexes": {},
      "foreignKeys": {
        "consent_user_id_users_id_fk": {
          "name": "consent_user_id_users_id_fk",
          "tableFrom": "consent",
          "tableTo": "users",
          "columnsFrom": [
            "user_id"
          ],
          "columnsTo": [
            "id"
          ],
          "onDelete": "cascade",
          "onUpdate": "no action"
        },
        "consent_client_id_oauth_clients_id_fk": {
          "name": "consent_client_id_oauth_clients_id_fk",
          "tableFrom": "consent",
          "tableTo": "oauth_clients",
          "columnsFrom": [
            "client_id"
          ],
          "columnsTo": [
            "id"
          ],
          "onDelete": "cascade",
          "onUpdate": "no action"
        }
      },
      "compositePrimaryKeys": {},
      "uniqueConstraints": {},
      "policies": {},
      "checkConstraints": {},
      "isRLSEnabled": false
    },
    "public.oauth_clients": {
      "name": "oauth_clients",
      "schema": "",
      "columns": {
        "id": {
          "name": "id",
          "type": "uuid",
          "primaryKey": true,
          "notNull": true,
          "default": "gen_random_uuid()"
        },
        "app_name": {
          "name": "app_name",
          "type": "varchar(50)",
          "primaryKey": false,
          "notNull": true
        },
        "client_id": {
          "name": "client_id",
          "type": "text",
          "primaryKey": false,
          "notNull": true
        },
        "client_secret": {
          "name": "client_secret",
          "type": "text",
          "primaryKey": false,
          "notNull": true
        },
        "website_url": {
          "name": "website_url",
          "type": "varchar(255)",
          "primaryKey": false,
          "notNull": true
        },
        "redirect_uris": {
          "name": "redirect_uris",
          "type": "text[]",
          "primaryKey": false,
          "notNull": true
        },
        "owner_user_id": {
          "name": "owner_user_id",
          "type": "uuid",
          "primaryKey": false,
          "notNull": true
        },
        "created_at": {
          "name": "created_at",
          "type": "timestamp",
          "primaryKey": false,
          "notNull": true,
          "default": "now()"
        }
      },
      "indexes": {},
      "foreignKeys": {
        "oauth_clients_owner_user_id_users_id_fk": {
          "name": "oauth_clients_owner_user_id_users_id_fk",
          "tableFrom": "oauth_clients",
          "tableTo": "users",
          "columnsFrom": [
            "owner_user_id"
          ],
          "columnsTo": [
            "id"
          ],
          "onDelete": "cascade",
          "onUpdate": "no action"
        }
      },
      "compositePrimaryKeys": {},
      "uniqueConstraints": {
        "oauth_clients_client_id_unique": {
          "name": "oauth_clients_client_id_unique",
          "nullsNotDistinct": false,
          "columns": [
            "client_id"
          ]
        }
      },
      "policies": {},
      "checkConstraints": {},
      "isRLSEnabled": false
    },
    "public.refresh_tokens": {
      "name": "refresh_tokens",
      "schema": "",
      "columns": {
        "id": {
          "name": "id",
          "type": "uuid",
          "primaryKey": true,
          "notNull": true,
          "default": "gen_random_uuid()"
        },
        "token": {
          "name": "token",
          "type": "text",
          "primaryKey": false,
          "notNull": true
        },
        "user_id": {
          "name": "user_id",
          "type": "uuid",
          "primaryKey": false,
          "notNull": true
        },
        "client_id": {
          "name": "client_id",
          "type": "uuid",
          "primaryKey": false,
          "notNull": true
        },
        "scopes": {
          "name": "scopes",
          "type": "text[]",
          "primaryKey": false,
          "notNull": true
        },
        "revoked": {
          "name": "revoked",
          "type": "boolean",
          "primaryKey": false,
          "notNull": true,
          "default": false
        },
        "expires_at": {
          "name": "expires_at",
          "type": "timestamp",
          "primaryKey": false,
          "notNull": true
        },
        "created_at": {
          "name": "created_at",
          "type": "timestamp",
          "primaryKey": false,
          "notNull": true,
          "default": "now()"
        }
      },
      "indexes": {},
      "foreignKeys": {
        "refresh_tokens_user_id_users_id_fk": {
          "name": "refresh_tokens_user_id_users_id_fk",
          "tableFrom": "refresh_tokens",
          "tableTo": "users",
          "columnsFrom": [
            "user_id"
          ],
          "columnsTo": [
            "id"
          ],
          "onDelete": "cascade",
          "onUpdate": "no action"
        },
        "refresh_tokens_client_id_oauth_clients_id_fk": {
          "name": "refresh_tokens_client_id_oauth_clients_id_fk",
          "tableFrom": "refresh_tokens",
          "tableTo": "oauth_clients",
          "columnsFrom": [
            "client_id"
          ],
          "columnsTo": [
            "id"
          ],
          "onDelete": "cascade",
          "onUpdate": "no action"
        }
      },
      "compositePrimaryKeys": {},
      "uniqueConstraints": {},
      "policies": {},
      "checkConstraints": {},
      "isRLSEnabled": false
    },
    "public.users": {
      "name": "users",
      "schema": "",
      "columns": {
        "id": {
          "name": "id",
          "type": "uuid",
          "primaryKey": true,
          "notNull": true,
          "default": "gen_random_uuid()"
        },
        "username": {
          "name": "username",
          "type": "varchar(20)",
          "primaryKey": false,
          "notNull": false
        },
        "fullname": {
          "name": "fullname",
          "type": "varchar(25)",
          "primaryKey": false,
          "notNull": true
        },
        "date_of_birth": {
          "name": "date_of_birth",
          "type": "date",
          "primaryKey": false,
          "notNull": true
        },
        "password": {
          "name": "password",
          "type": "text",
          "primaryKey": false,
          "notNull": true
        },
        "salt": {
          "name": "salt",
          "type": "text",
          "primaryKey": false,
          "notNull": true
        },
        "gender": {
          "name": "gender",
          "type": "gender",
          "typeSchema": "public",
          "primaryKey": false,
          "notNull": true
        },
        "email": {
          "name": "email",
          "type": "varchar(255)",
          "primaryKey": false,
          "notNull": true
        },
        "email_verified": {
          "name": "email_verified",
          "type": "boolean",
          "primaryKey": false,
          "notNull": true,
          "default": false
        },
        "created_at": {
          "name": "created_at",
          "type": "timestamp",
          "primaryKey": false,
          "notNull": true,
          "default": "now()"
        },
        "updated_at": {
          "name": "updated_at",
          "type": "timestamp",
          "primaryKey": false,
          "notNull": false
        }
      },
      "indexes": {},
      "foreignKeys": {},
      "compositePrimaryKeys": {},
      "uniqueConstraints": {
        "users_username_unique": {
          "name": "users_username_unique",
          "nullsNotDistinct": false,
          "columns": [
            "username"
          ]
        },
        "users_email_unique": {
          "name": "users_email_unique",
          "nullsNotDistinct": false,
          "columns": [
            "email"
          ]
        }
      },
      "policies": {},
      "checkConstraints": {},
      "isRLSEnabled": false
    }
  },
  "enums": {
    "public.gender": {
      "name": "gender",
      "schema": "public",
      "values": [
        "male",
        "female",
        "other"
      ]
    }
  },
  "schemas": {},
  "sequences": {},
  "roles": {},
  "policies": {},
  "views": {},
  "_meta": {
    "columns": {},
    "schemas": {},
    "tables": {}
  }
}